{
  "name" : "cangie-bear",
  "title" : "Cangie Bear",
  "subtitle" : "the dog",
  "author" : "me",
  "created" : 1721231096421,
  "content" : {
    "time" : 1721231095440,
    "blocks" : [ {
      "id" : "jX-vtO90vm",
      "type" : "paragraph",
      "data" : {
        "text" : "This is a test.&nbsp;"
      },
      "tunes" : {
        "anyTuneName" : {
          "alignment" : "left"
        }
      }
    }, {
      "id" : "X_wQHgv6TO",
      "type" : "header",
      "data" : {
        "text" : "Hello",
        "level" : 2
      },
      "tunes" : {
        "anyTuneName" : {
          "alignment" : "left"
        }
      }
    } ],
    "version" : "2.30.2"
  },
  "properties" : {
    "background-image" : "https://images.pexels.com/photos/33109/fall-autumn-red-season.jpg"
  },
  "path" : "content/cangie-bear.json"
}